Workbook

Sheet POUR DEMARRER
B3: A quoi sert le plan de développement des compétences ? Le plan est un outil qui présente l'ensemble des formations décidées pour l'année à venir, compte tenu des priorités stratégiques de votre organisation et des besoins de formation de vos salariés recueillis lors des entretiens professionnels. Il contient généralement : • les formations obligatoires : indispensables à l'exercice d’une activité ou d’une fonction (habilitations, certificats d'aptitude, prévention en matière d’hygiène et de sécurité au travail...) • les autres actions de formation : adaptation au poste de travail, montée en compétences et en qualification, actions de professionnalisation, apprentissage, validations des acquis de l'expérience (VAE), bilans de compétences, lutte contre l'illettrisme... L'outil qui vous est proposé ici est un modèle de plan de développement des compétences.
B5: Les avantages d’établir un plan de développement des compétences : • Attirer et fidéliser les talents en renvoyant l’image d’une entreprise dynamique qui facilite l’évolution professionnelle des salariés • Rester compétitif en anticipant les compétences dont vous aurez besoin face aux transformations sociales, numériques et environnementales • Organiser et formaliser annuellement les actions de formation à destination des salariés • Faciliter la préparation des entretiens professionnels, obligatoires tous les 2 ans.
B7: Tout ce qu'il faut savoir sur le Plan de Développement des Compétences se trouve ICI
B12: Comment faire une demande de Prise en Charge ?
B14: Accédez à votre espace Employeurs, experts-comptables, organismes de formation, accédez en quelques clics à vos outils en ligne.

Sheet PDC simplifié
C2: RAISON SOCIALE | G2: Mon conseiller AKTO
C4: N° adhérent AKTO (N° SIRET si inconnu) | G4: Mail de mon conseiller
C6: Branche | G6: Téléphone de mon conseiller
C9: Ce fichier n'est pas une demande de prise en charge mais un outil d'aide à l'inventaire de vos besoins en formation.
A10: POUR UNE FORMATION INDIVIDUELLE | D10: POUR UNE FORMATION EN GROUPE | E10: FORMATION | M10: ORGANISME | P10: COÛTS
A11: Type de contrat | B11: CSP | C11: Le salarié a-t-il déjà bénéficié d'une formation non-obligatoire depuis 6 ans ? | D11: Nbre de stagiaires | E11: N° de dossier | F11: Intitulé Formation | G11: Date début | H11: Date fin | I11: Durée en heures | J11: Lieu de formation | K11: Formation obligatoire | L11: Code RNCP (Si concerné) | M11: Raison sociale OF | N11: CP OF | O11: Ville OF | P11: Coût pédagogique (H.T.) | Q11: Rémunération | R11: Divers | S11: Sous-total
A12: Contrat de professionnalisation | B12: Ouvrier qualifié et HQ | C12: Non | D12: 20 | E12: X0001 | F12: Exemple : HYGIENE AGROALIMENTAIRE | G12: 13/02/2023 | H12: 14/02/2023 | I12: 7 | J12: Externe | K12: Oui | L12: 34306 | M12: HYDIAC | N12: 35000 | O12: RENNES | P12: 100 | Q12: 20 | R12: 30 | S12: =SUM(P12:R12) -> 150
S13: =SUM(P13:R13) -> 0
S14: =SUM(P14:R14) -> 0
S15: =SUM(P15:R15) -> 0
S16: =SUM(P16:R16) -> 0
S17: =SUM(P17:R17) -> 0
S18: =SUM(P18:R18) -> 0
S19: =SUM(P19:R19) -> 0
S20: =SUM(P20:R20) -> 0
S21: =SUM(P21:R21) -> 0
S22: =SUM(P22:R22) -> 0
S23: =SUM(P23:R23) -> 0
S24: =SUM(P24:R24) -> 0
... S29: =SUM(P29:R29) -> 0
O31: Total : | P31: =SUM(P12:P23) -> 100 | Q31: =SUM(Q12:Q23) -> 20 | R31: =SUM(R12:R23) -> 30 | S31: =SUM(P31:R31) -> 150

Sheet NOTICE simplifiée
D4: Pour faire vos demandes de prise en charge, connectez-vous à Mon Espace
B7: BENEFICIAIRE DE LA FORMATION Individuel | C7: TYPE DE CONTRAT | E7: Préciser le type de contrat de travail du salarié en formation
C8: CSP | E8: Catégorie Sociale du salarié
C9: FORMATION NON-OBLIGATOIRE DEPUIS 6 ANS | E9: Indiquer si le salarié a eu une formation non-obligatoire au cours des 6 dernières années
B10: BENEFICIAIRES DE LA FORMATION Groupe | C10: NBRE DE STAGIAIRES | E10: Préciser le nombre de vos salariés bénéficiant de la formation en groupe
B11: FORMATION | C11: N° de dossier | E11: Renseigner le n° de dossier AKTO
C12: INTITULE FORMATION | E12: Renseigner l'intitulé de l'action de formation ou d'alternance
C13: DATE DEBUT | E13: Date du 1er jour de formation
C14: DATE FIN | E14: Date du dernier jour de formation
C15: DUREE H | E15: durée totale de la formation en heure
C16: TYPE FORMATION | E16: indiquer s'il s'agit d'une action de formation : - Interne : le formateur et le lieu de formation sont de l'entreprise - Externe : le formateur et le lieu de formation sont extérieurs à l'entreprise - Intra : Le formateur est extérieur et le lieu de formation est dans l'entreprise
C17: RNCP | E17: Le RNCP (Répertoire national des certifications professionnelles) recense la liste de tous les diplômes et titres à vocation professionnelle. L'inscription au RNCP atteste d'un niveau de qualification officiel. Informations FRANCE COMPETENCES : https://www.francecompetences.fr/recherche_certificationprofessionnelle
B18: ORGANISME | C18: RAISON SOCIALE OF | E18: Renseigner la raison sociale de l'organisme de formation correspondant à la convention de formation
C19: CP OF | E19: Code postal de l'organisme de formation
C20: VILLE OF | E20: Ville de l'organisme de formation
B21: COÛTS | C21: COUT PEDAGOGIQUE | E21: Coût en euros de l'action de formation indiquée à la convention de formation
C22: REMUNERATION | E22: Rémunération du salarié correspondant à la durée de formation (en général = coût horaire X durée en H X taux de charges patronales x taux de congés)
C23: DIVERS | E23: Coût de frais divers du salarié dépendant de la participation à l'action de formation

Sheet PDC-détaillé
B1: Le plan de développement des compétences : un levier de performance L’employeur a deux obligations en matière de formation professionnelle : l’adaptation au poste de travail et le maintien dans l’emploi des salariés. Pour y répondre, il existe le plan de développement des compétences. Remplaçant depuis le 1er janvier 2019 le « plan de formation », le plan de développement des compétences est bien plus qu'une simple réponse légale : il fait entrer l'entreprise dans une logique d'anticipation proactive.
C3: RAISON SOCIALE | K3: Mon conseiller AKTO
C5: N° adhérent AKTO (N° SIRET si inconnu) | K5: Mail de mon conseiller
C7: Branche | K7: Téléphone de mon conseiller
C10: Ce fichier n'est pas une demande de prise en charge mais un outil d'aide à l'inventaire de vos besoins en formation. Les informations demandées dans cette version correspondent à la législation en vigueur pour les demandes de prises en charge
A11: FORMATION | N11: ORGANISME | V11: BENEFICIAIRES DE LA FORMATION Groupe | W11: BENEFICIAIRE DE LA FORMATION Individuel | Z11: FINANCEMENTS | AB11: COÛTS
A12: N° de Dossier | B12: INTITULE FORMATION | C12: DATE DEBUT | D12: DATE FIN | E12: DUREE H | F12: TYPE FORMATION | G12: FORMACODE Centre Inffo | H12: CODE RNCP France Compétences | I12: FORMATION OBLIGATOIRE | J12: DISPOSITIF | K12: DOMAINE | L12: LIEU | M12: CERTIFIANT | N12: RAISON SOCIALE OF | O12: SIRET OF | P12: NDA | Q12: QUALIOPI | R12: ADRESSE 1 OF | S12: ADRESSE 2 OF | T12: CP OF | U12: VILLE OF | V12: Nbre de stagiaires | W12: Type de contrat | X12: CSP | Y12: Le salarié a-t-il déjà bénéficier d'une formation non-obligatoire depuis 6 ans ? | Z12: BUDGET | AA12: FINANCEMENTS AUTRES | AB12: COUT PEDAGOGIQUE | AC12: REMUNERATION | AD12: HEBERGEMENT | AE12: REPAS | AF12: TRANSPORT | AG12: DIVERS | AH12: SOUS-TOTAL
A14: eXemple 001 | B14: HYGIENE AGROALIMENTAIRE | C14: 13/02/2023 | D14: 14/02/2023 | E14: 7 | F14: Externe INTRA | G14: 21570 | I14: NON | J14: Action de formation | K14: AGROALIMENTAIRE | L14: Présentiel | M14: Non | N14: HYDIAC | O14: 75210179000034 | P14: 53350912935 | Q14: Non | R14: 4 B RUE DU BIGNON | S14: CENTRE D'AFFAIRE B2 | T14: 35000 | U14: RENNES | V14: 20 | W14: Contrat de professionnalisation | X14: Ouvrier qualifié et HQ | Y14: Oui | Z14: Action co | AA14: CPF | AB14: 195.75 | AC14: 131.53 | AD14: 8.5 | AE14: 9.5 | AF14: 22 | AG14: 23 | AH14: =SUM(AB14:AG14) -> 390.28
A15: ='PDC simplifié'!E13 -> 0 | B15: ='PDC simplifié'!F13 -> 0 | C15: ='PDC simplifié'!G13 -> 0 | D15: ='PDC simplifié'!H13 -> 0 | E15: ='PDC simplifié'!I13 -> 0 | F15: ='PDC simplifié'!J13 -> 0 | H15: ='PDC simplifié'!L13 -> 0 | I15: ='PDC simplifié'!K13 -> 0 | N15: ='PDC simplifié'!M13 -> 0 | T15: ='PDC simplifié'!N13 -> 0 | U15: ='PDC simplifié'!O13 -> 0 | V15: ='PDC simplifié'!D13 -> 0 | W15: ='PDC simplifié'!A13 -> 0 | X15: ='PDC simplifié'!B13 -> 0 | Y15: ='PDC simplifié'!C13 -> 0 | AB15: ='PDC simplifié'!P13 -> 0 | AC15: ='PDC simplifié'!Q13 -> 0 | AG15: ='PDC simplifié'!Q13 -> 0 | AH15: =SUM(AB15:AG15) -> 0
A16: ='PDC simplifié'!E14 -> 0 | B16: ='PDC simplifié'!F14 -> 0 | C16: ='PDC simplifié'!G14 -> 0 | D16: ='PDC simplifié'!H14 -> 0 | E16: ='PDC simplifié'!I14 -> 0 | F16: ='PDC simplifié'!J14 -> 0 | H16: ='PDC simplifié'!L14 -> 0 | I16: ='PDC simplifié'!K14 -> 0 | N16: ='PDC simplifié'!M14 -> 0 | T16: ='PDC simplifié'!N14 -> 0 | U16: ='PDC simplifié'!O14 -> 0 | V16: ='PDC simplifié'!D14 -> 0 | W16: ='PDC simplifié'!A14 -> 0 | X16: ='PDC simplifié'!B14 -> 0 | Y16: ='PDC simplifié'!C14 -> 0 | AB16: ='PDC simplifié'!P14 -> 0 | AC16: ='PDC simplifié'!Q14 -> 0 | AG16: ='PDC simplifié'!Q14 -> 0 | AH16: =SUM(AB16:AG16) -> 0
A17: ='PDC simplifié'!E15 -> 0 | B17: ='PDC simplifié'!F15 -> 0 | C17: ='PDC simplifié'!G15 -> 0 | D17: ='PDC simplifié'!H15 -> 0 | E17: ='PDC simplifié'!I15 -> 0 | F17: ='PDC simplifié'!J15 -> 0 | H17: ='PDC simplifié'!L15 -> 0 | I17: ='PDC simplifié'!K15 -> 0 | N17: ='PDC simplifié'!M15 -> 0 | T17: ='PDC simplifié'!N15 -> 0 | U17: ='PDC simplifié'!O15 -> 0 | V17: ='PDC simplifié'!D15 -> 0 | W17: ='PDC simplifié'!A15 -> 0 | X17: ='PDC simplifié'!B15 -> 0 | Y17: ='PDC simplifié'!C15 -> 0 | AB17: ='PDC simplifié'!P15 -> 0 | AC17: ='PDC simplifié'!Q15 -> 0 | AG17: ='PDC simplifié'!Q15 -> 0 | AH17: =SUM(AB17:AG17) -> 0
A18: ='PDC simplifié'!E16 -> 0 | B18: ='PDC simplifié'!F16 -> 0 | C18: ='PDC simplifié'!G16 -> 0 | D18: ='PDC simplifié'!H16 -> 0 | E18: ='PDC simplifié'!I16 -> 0 | F18: ='PDC simplifié'!J16 -> 0 | H18: ='PDC simplifié'!L16 -> 0 | I18: ='PDC simplifié'!K16 -> 0 | N18: ='PDC simplifié'!M16 -> 0 | T18: ='PDC simplifié'!N16 -> 0 | U18: ='PDC simplifié'!O16 -> 0 | V18: ='PDC simplifié'!D16 -> 0 | W18: ='PDC simplifié'!A16 -> 0 | X18: ='PDC simplifié'!B16 -> 0 | Y18: ='PDC simplifié'!C16 -> 0 | AB18: ='PDC simplifié'!P16 -> 0 | AC18: ='PDC simplifié'!Q16 -> 0 | AG18: ='PDC simplifié'!Q16 -> 0 | AH18: =SUM(AB18:AG18) -> 0
A19: ='PDC simplifié'!E17 -> 0 | B19: ='PDC simplifié'!F17 -> 0 | C19: ='PDC simplifié'!G17 -> 0 | D19: ='PDC simplifié'!H17 -> 0 | E19: ='PDC simplifié'!I17 -> 0 | F19: ='PDC simplifié'!J17 -> 0 | H19: ='PDC simplifié'!L17 -> 0 | I19: ='PDC simplifié'!K17 -> 0 | N19: ='PDC simplifié'!M17 -> 0 | T19: ='PDC simplifié'!N17 -> 0 | U19: ='PDC simplifié'!O17 -> 0 | V19: ='PDC simplifié'!D17 -> 0 | W19: ='PDC simplifié'!A17 -> 0 | X19: ='PDC simplifié'!B17 -> 0 | Y19: ='PDC simplifié'!C17 -> 0 | AB19: ='PDC simplifié'!P17 -> 0 | AC19: ='PDC simplifié'!Q17 -> 0 | AG19: ='PDC simplifié'!Q17 -> 0 | AH19: =SUM(AB19:AG19) -> 0
A20: ='PDC simplifié'!E18 -> 0 | B20: ='PDC simplifié'!F18 -> 0 | C20: ='PDC simplifié'!G18 -> 0 | D20: ='PDC simplifié'!H18 -> 0 | E20: ='PDC simplifié'!I18 -> 0 | F20: ='PDC simplifié'!J18 -> 0 | H20: ='PDC simplifié'!L18 -> 0 | I20: ='PDC simplifié'!K18 -> 0 | N20: ='PDC simplifié'!M18 -> 0 | T20: ='PDC simplifié'!N18 -> 0 | U20: ='PDC simplifié'!O18 -> 0 | V20: ='PDC simplifié'!D18 -> 0 | W20: ='PDC simplifié'!A18 -> 0 | X20: ='PDC simplifié'!B18 -> 0 | Y20: ='PDC simplifié'!C18 -> 0 | AB20: ='PDC simplifié'!P18 -> 0 | AC20: ='PDC simplifié'!Q18 -> 0 | AG20: ='PDC simplifié'!Q18 -> 0 | AH20: =SUM(AB20:AG20) -> 0
A21: ='PDC simplifié'!E19 -> 0 | B21: ='PDC simplifié'!F19 -> 0 | C21: ='PDC simplifié'!G19 -> 0 | D21: ='PDC simplifié'!H19 -> 0 | E21: ='PDC simplifié'!I19 -> 0 | F21: ='PDC simplifié'!J19 -> 0 | H21: ='PDC simplifié'!L19 -> 0 | I21: ='PDC simplifié'!K19 -> 0 | N21: ='PDC simplifié'!M19 -> 0 | T21: ='PDC simplifié'!N19 -> 0 | U21: ='PDC simplifié'!O19 -> 0 | V21: ='PDC simplifié'!D19 -> 0 | W21: ='PDC simplifié'!A19 -> 0 | X21: ='PDC simplifié'!B19 -> 0 | Y21: ='PDC simplifié'!C19 -> 0 | AB21: ='PDC simplifié'!P19 -> 0 | AC21: ='PDC simplifié'!Q19 -> 0 | AG21: ='PDC simplifié'!Q19 -> 0 | AH21: =SUM(AB21:AG21) -> 0
A22: ='PDC simplifié'!E20 -> 0 | B22: ='PDC simplifié'!F20 -> 0 | C22: ='PDC simplifié'!G20 -> 0 | D22: ='PDC simplifié'!H20 -> 0 | E22: ='PDC simplifié'!I20 -> 0 | F22: ='PDC simplifié'!J20 -> 0 | H22: ='PDC simplifié'!L20 -> 0 | I22: ='PDC simplifié'!K20 -> 0 | N22: ='PDC simplifié'!M20 -> 0 | T22: ='PDC simplifié'!N20 -> 0 | U22: ='PDC simplifié'!O20 -> 0 | V22: ='PDC simplifié'!D20 -> 0 | W22: ='PDC simplifié'!A20 -> 0 | X22: ='PDC simplifié'!B20 -> 0 | Y22: ='PDC simplifié'!C20 -> 0 | AB22: ='PDC simplifié'!P20 -> 0 | AC22: ='PDC simplifié'!Q20 -> 0 | AG22: ='PDC simplifié'!Q20 -> 0 | AH22: =SUM(AB22:AG22) -> 0
A23: ='PDC simplifié'!E21 -> 0 | B23: ='PDC simplifié'!F21 -> 0 | C23: ='PDC simplifié'!G21 -> 0 | D23: ='PDC simplifié'!H21 -> 0 | E23: ='PDC simplifié'!I21 -> 0 | F23: ='PDC simplifié'!J21 -> 0 | H23: ='PDC simplifié'!L21 -> 0 | I23: ='PDC simplifié'!K21 -> 0 | N23: ='PDC simplifié'!M21 -> 0 | T23: ='PDC simplifié'!N21 -> 0 | U23: ='PDC simplifié'!O21 -> 0 | V23: ='PDC simplifié'!D21 -> 0 | W23: ='PDC simplifié'!A21 -> 0 | X23: ='PDC simplifié'!B21 -> 0 | Y23: ='PDC simplifié'!C21 -> 0 | AB23: ='PDC simplifié'!P21 -> 0 | AC23: ='PDC simplifié'!Q21 -> 0 | AG23: ='PDC simplifié'!Q21 -> 0 | AH23: =SUM(AB23:AG23) -> 0
A24: ='PDC simplifié'!E22 -> 0 | B24: ='PDC simplifié'!F22 -> 0 | C24: ='PDC simplifié'!G22 -> 0 | D24: ='PDC simplifié'!H22 -> 0 | E24: ='PDC simplifié'!I22 -> 0 | F24: ='PDC simplifié'!J22 -> 0 | H24: ='PDC simplifié'!L22 -> 0 | I24: ='PDC simplifié'!K22 -> 0 | N24: ='PDC simplifié'!M22 -> 0 | T24: ='PDC simplifié'!N22 -> 0 | U24: ='PDC simplifié'!O22 -> 0 | V24: ='PDC simplifié'!D22 -> 0 | W24: ='PDC simplifié'!A22 -> 0 | X24: ='PDC simplifié'!B22 -> 0 | Y24: ='PDC simplifié'!C22 -> 0 | AB24: ='PDC simplifié'!P22 -> 0 | AC24: ='PDC simplifié'!Q22 -> 0 | AG24: ='PDC simplifié'!Q22 -> 0 | AH24: =SUM(AB24:AG24) -> 0
A25: ='PDC simplifié'!E23 -> 0 | B25: ='PDC simplifié'!F23 -> 0 | C25: ='PDC simplifié'!G23 -> 0 | D25: ='PDC simplifié'!H23 -> 0 | E25: ='PDC simplifié'!I23 -> 0 | F25: ='PDC simplifié'!J23 -> 0 | H25: ='PDC simplifié'!L23 -> 0 | I25: ='PDC simplifié'!K23 -> 0 | N25: ='PDC simplifié'!M23 -> 0 | T25: ='PDC simplifié'!N23 -> 0 | U25: ='PDC simplifié'!O23 -> 0 | V25: ='PDC simplifié'!D23 -> 0 | W25: ='PDC simplifié'!A23 -> 0 | X25: ='PDC simplifié'!B23 -> 0 | Y25: ='PDC simplifié'!C23 -> 0 | AB25: ='PDC simplifié'!P23 -> 0 | AC25: ='PDC simplifié'!Q23 -> 0 | AG25: ='PDC simplifié'!Q23 -> 0 | AH25: =SUM(AB25:AG25) -> 0
A26: ='PDC simplifié'!E30 -> 0 | B26: ='PDC simplifié'!F30 -> 0 | C26: ='PDC simplifié'!G30 -> 0 | D26: ='PDC simplifié'!H30 -> 0 | E26: ='PDC simplifié'!I30 -> 0 | F26: ='PDC simplifié'!J30 -> 0 | H26: ='PDC simplifié'!L30 -> 0 | I26: ='PDC simplifié'!K30 -> 0 | N26: ='PDC simplifié'!M30 -> 0 | T26: ='PDC simplifié'!N30 -> 0 | U26: ='PDC simplifié'!O30 -> 0 | V26: ='PDC simplifié'!D30 -> 0 | W26: ='PDC simplifié'!A30 -> 0 | X26: ='PDC simplifié'!B30 -> 0 | Y26: ='PDC simplifié'!C30 -> 0 | AB26: ='PDC simplifié'!P30 -> 0 | AC26: ='PDC simplifié'!Q30 -> 0 | AG26: ='PDC simplifié'!Q30 -> 0 | AH26: =SUM(AB26:AG26) -> 0
A27: ='PDC simplifié'!E31 -> 0 | B27: ='PDC simplifié'!F31 -> 0 | C27: ='PDC simplifié'!G31 -> 0 | D27: ='PDC simplifié'!H31 -> 0 | E27: ='PDC simplifié'!I31 -> 0 | F27: ='PDC simplifié'!J31 -> 0 | H27: ='PDC simplifié'!L31 -> 0 | I27: ='PDC simplifié'!K31 -> 0 | N27: ='PDC simplifié'!M31 -> 0 | T27: ='PDC simplifié'!N31 -> 0 | U27: ='PDC simplifié'!O31 -> Total : | V27: ='PDC simplifié'!D31 -> 0 | W27: ='PDC simplifié'!A31 -> 0 | X27: ='PDC simplifié'!B31 -> 0 | Y27: ='PDC simplifié'!C31 -> 0 | AH27: =SUM(AB27:AG27) -> 0
A28: ='PDC simplifié'!E32 -> 0 | B28: ='PDC simplifié'!F32 -> 0 | C28: ='PDC simplifié'!G32 -> 0 | D28: ='PDC simplifié'!H32 -> 0 | E28: ='PDC simplifié'!I32 -> 0 | F28: ='PDC simplifié'!J32 -> 0 | H28: ='PDC simplifié'!L32 -> 0 | I28: ='PDC simplifié'!K32 -> 0 | N28: ='PDC simplifié'!M32 -> 0 | T28: ='PDC simplifié'!N32 -> 0 | U28: ='PDC simplifié'!O32 -> 0 | V28: ='PDC simplifié'!D32 -> 0 | W28: ='PDC simplifié'!A32 -> 0 | X28: ='PDC simplifié'!B32 -> 0 | Y28: ='PDC simplifié'!C32 -> 0 | AB28: ='PDC simplifié'!P32 -> 0 | AC28: ='PDC simplifié'!Q32 -> 0 | AG28: ='PDC simplifié'!Q32 -> 0 | AH28: =SUM(AB28:AG28) -> 0
A29: ='PDC simplifié'!E33 -> 0 | B29: ='PDC simplifié'!F33 -> 0 | C29: ='PDC simplifié'!G33 -> 0 | D29: ='PDC simplifié'!H33 -> 0 | E29: ='PDC simplifié'!I33 -> 0 | F29: ='PDC simplifié'!J33 -> 0 | H29: ='PDC simplifié'!L33 -> 0 | I29: ='PDC simplifié'!K33 -> 0 | N29: ='PDC simplifié'!M33 -> 0 | T29: ='PDC simplifié'!N33 -> 0 | U29: ='PDC simplifié'!O33 -> 0 | V29: ='PDC simplifié'!D33 -> 0 | W29: ='PDC simplifié'!A33 -> 0 | X29: ='PDC simplifié'!B33 -> 0 | Y29: ='PDC simplifié'!C33 -> 0 | AB29: ='PDC simplifié'!P33 -> 0 | AC29: ='PDC simplifié'!Q33 -> 0 | AG29: ='PDC simplifié'!Q33 -> 0 | AH29: =SUM(AB29:AG29) -> 0
A30: ='PDC simplifié'!E34 -> 0 | B30: ='PDC simplifié'!F34 -> 0 | C30: ='PDC simplifié'!G34 -> 0 | D30: ='PDC simplifié'!H34 -> 0 | E30: ='PDC simplifié'!I34 -> 0 | F30: ='PDC simplifié'!J34 -> 0 | H30: ='PDC simplifié'!L34 -> 0 | I30: ='PDC simplifié'!K34 -> 0 | N30: ='PDC simplifié'!M34 -> 0 | T30: ='PDC simplifié'!N34 -> 0 | U30: ='PDC simplifié'!O34 -> 0 | V30: ='PDC simplifié'!D34 -> 0 | W30: ='PDC simplifié'!A34 -> 0 | X30: ='PDC simplifié'!B34 -> 0 | Y30: ='PDC simplifié'!C34 -> 0 | AB30: ='PDC simplifié'!P34 -> 0 | AC30: ='PDC simplifié'!Q34 -> 0 | AG30: ='PDC simplifié'!Q34 -> 0 | AH30: =SUM(AB30:AG30) -> 0
A31: ='PDC simplifié'!E35 -> 0 | B31: ='PDC simplifié'!F35 -> 0 | C31: ='PDC simplifié'!G35 -> 0 | D31: ='PDC simplifié'!H35 -> 0 | E31: ='PDC simplifié'!I35 -> 0 | F31: ='PDC simplifié'!J35 -> 0 | H31: ='PDC simplifié'!L35 -> 0 | I31: ='PDC simplifié'!K35 -> 0 | N31: ='PDC simplifié'!M35 -> 0 | T31: ='PDC simplifié'!N35 -> 0 | U31: ='PDC simplifié'!O35 -> 0 | V31: ='PDC simplifié'!D35 -> 0 | W31: ='PDC simplifié'!A35 -> 0 | X31: ='PDC simplifié'!B35 -> 0 | Y31: ='PDC simplifié'!C35 -> 0 | AB31: ='PDC simplifié'!P35 -> 0 | AC31: ='PDC simplifié'!Q35 -> 0 | AG31: ='PDC simplifié'!Q35 -> 0 | AH31: =SUM(AB31:AG31) -> 0
A32: ='PDC simplifié'!E36 -> 0 | B32: ='PDC simplifié'!F36 -> 0 | C32: ='PDC simplifié'!G36 -> 0 | D32: ='PDC simplifié'!H36 -> 0 | E32: ='PDC simplifié'!I36 -> 0 | F32: ='PDC simplifié'!J36 -> 0 | H32: ='PDC simplifié'!L36 -> 0 | I32: ='PDC simplifié'!K36 -> 0 | N32: ='PDC simplifié'!M36 -> 0 | T32: ='PDC simplifié'!N36 -> 0 | U32: ='PDC simplifié'!O36 -> 0 | V32: ='PDC simplifié'!D36 -> 0 | W32: ='PDC simplifié'!A36 -> 0 | X32: ='PDC simplifié'!B36 -> 0 | Y32: ='PDC simplifié'!C36 -> 0 | AB32: ='PDC simplifié'!P36 -> 0 | AC32: ='PDC simplifié'!Q36 -> 0 | AG32: ='PDC simplifié'!Q36 -> 0 | AH32: =SUM(AB32:AG32) -> 0
A33: ='PDC simplifié'!E37 -> 0 | B33: ='PDC simplifié'!F37 -> 0 | C33: ='PDC simplifié'!G37 -> 0 | D33: ='PDC simplifié'!H37 -> 0 | E33: ='PDC simplifié'!I37 -> 0 | F33: ='PDC simplifié'!J37 -> 0 | H33: ='PDC simplifié'!L37 -> 0 | I33: ='PDC simplifié'!K37 -> 0 | N33: ='PDC simplifié'!M37 -> 0 | T33: ='PDC simplifié'!N37 -> 0 | U33: ='PDC simplifié'!O37 -> 0 | V33: ='PDC simplifié'!D37 -> 0 | W33: ='PDC simplifié'!A37 -> 0 | X33: ='PDC simplifié'!B37 -> 0 | Y33: ='PDC simplifié'!C37 -> 0 | AB33: ='PDC simplifié'!P37 -> 0 | AC33: ='PDC simplifié'!Q37 -> 0 | AG33: ='PDC simplifié'!Q37 -> 0 | AH33: =SUM(AB33:AG33) -> 0
AA35: TOTAL : | AB35: =SUM(AB14:AB24) -> 195.75 | AC35: =SUM(AC14:AC24) -> 131.53 | AD35: =SUM(AD14:AD24) -> 8.5 | AE35: =SUM(AE14:AE24) -> 9.5 | AF35: =SUM(AF14:AF24) -> 22 | AG35: =SUM(AG14:AG24) -> 23 | AH35: =SUM(AH14:AH24) -> 390.28

Sheet NOTICE détaillée
D3: * | E3: Données obligatoires dans la cadre d'une demande de prise en charge par un OPCO et télétransmises auprès des services d'état
E4: Menu déroulant permettant de choisir parmi un référentiel défini
E5: données complémentaires
D7: Pour faire vos demandes de prise en charge, connectez-vous à Mon Espace
B9: FORMATION | C9: INTITULE FORMATION | D9: * | E9: Renseigner l'intitulé de l'action de formation ou d'alternance
C10: DATE DEBUT | D10: * | E10: Date du 1er jour de formation
C11: DATE FIN | D11: * | E11: Date du dernier jour de formation
C12: DUREE H | D12: * | E12: durée totale de la formation en heure
C13: TYPE FORMATION | E13: indiquer s'il s'agit d'une action de formation : - interne à l'entreprise avec un formateur de l'entreprise, - Intra à l'entreprise (en général dans les locaux de l'entreprise) et concernant un public de l'entreprise, le formateur est extérieur à l'entreprise, - Inter à l'entreprise (en général hors des locaux de l'entreprise) et concernant un public de diverses provenance, le formateur est extérieur à l'entreprise. | F13: menu déroulant
C14: FORMACODE Centre Inffo | D14: * | E14: Le Formacode® est un outil d’indexation et de référence pour tous les acteurs de la formation professionnelle et permettant la recherche d’information dans un système documentaire, sur tous supports. Le Formacode® est utile aux entreprises, organismes de formation, gestionnaires, financeurs, aux relais d’information sur la formation professionnelle, aux conseillers d’orientation. renseigner le code à 5 chiffres | F14: alphnumérique 5 position
C15: DOMAINE | D15: * | E15: Correspond à l'un des 65 champs sémantiques du FORMACODE | F15: menu déroulant
C16: CERTIFIANT | D16: * | E16: Les formations certifiantes ou qualifiantes sont celles qui mènent à un diplôme d’Etat, un titre ou une certification de qualification professionnelle (CQP), Il s’agit de certifications enregistrées au Répertoire National des Certifications Professionnelles (RNCP). | F16: Oui/Non
C17: RNCP | D17: * | E17: Le RNCP (Répertoire national des certifications professionnelles) recense la liste de tous les diplômes et titres à vocation professionnelle. L'inscription au RNCP atteste d'un niveau de qualification officiel. Informations FRANCE COMPETENCES : https://www.francecompetences.fr/recherche-resultats/ Obligatoire si l'action de formation est certifiante
B18: ORGANISME | C18: RAISON SOCIALE OF | D18: * | E18: Renseigner la raison sociale de l'organisme de formation correspondant à la convention de formation
C19: SIRET OF | D19: * | E19: indiquer le n° SIRET de l'organisme de formation correspondant à la convention de formation
C20: NDA | D20: * | E20: indiquer le n° de Déclaration d'activité des formateurs ou organismes de formation (NDA) indiqué à la convention de formation
C21: ADRESSE 1 OF | D21: * | E21: Adresse de l'organisme de formation
C22: ADRESSE 2 OF | E22: Complément d'adresse de l'organisme de formation (batiment, étage, zone d'activité … etc.)
C23: CP OF | D23: * | E23: Code postal de l'organisme de formation | F23: 00000
C24: VILLE OF | D24: * | E24: Ville de l'organisme de formation
B25: BENEFICIAIRES DE LA FORMATION Groupe | C25: NBRE DE STAGIAIRES | E25: Préciser le nombre de vos salariés bénéficiant de la formation
B26: BENEFICIAIRE DE LA FORMATION Individuel | C26: TYPE DE CONTRAT | E26: Préciser le type de contrat de travail du salarié en formation | F26: menu déroulant
C27: CSP | D27: * | E27: Catégorie Sociale du salarié
C28: FORMATION NON-OBLIGATOIRE DEPUIS 6 ANS | E28: Indiquer si le salarié a eu une formation non-obligatoire au cours des 6 dernières années
B29: COUTS | C29: COUT PEDAGOGIQUE | D29: * | E29: Coût en euros de l'action de formation indiquée à la convention de formation
C30: REMUNERATION | D30: * | E30: Rémunération du salarié correspondant à la durée de formation (en général = coût horaire X durée en H X taux de charges patronales x taux de congés)
C31: HEBERGEMENT | E31: Coût de frais d'hébergement du salarié dépendant de la participation à l'action de formation, hôtel …
C32: REPAS | E32: Coût de frais de restauration du salarié dépendant de la participation à l'action de formation, restaurant, plateaux repas …
C33: TRANSPORT | E33: Coût de frais de déplacement du salarié dépendant de la participation à l'action de formation, Train, frais kilométriques, transport en commun ... pour se rendre à la formation.
C34: DIVERS | E34: Coût de frais divers du salarié dépendant de la participation à l'action de formation

Sheet Feuil1
A1: Branche | B1: Type de formation | C1: CSP | D1: Domaine | E1: Réponse | F1: Type de formation | G1: Contrat | H1: Budget | I1: FINANCEMENTS AUTRES | J1: Dispositif | K1: lieu
A2: AUTOROUTES | B2: Externe | C2: Agent de maîtrise | D2: ACTION SOCIALE | E2: Oui | F2: Externe INTRA | H2: Actions Collectives | I2: CPF | J2: Action de formation | K2: Présentiel
A3: CAFÉTÉRIAS | B3: Interne | C3: Dirigeant salarié | D3: ACTIVITE PHYSIQUE ET SPORTIVE | E3: Non | F3: Externe INTER | G3: CDD | H3: EDEC | I3: Pôle Emploi | J3: Actions Collectives | K3: Distanciel
A4: COMMERCES DE GROS | C4: Employé | D4: AGRICULTURE PRODUCTION VEGETALE | F4: INTERNE | G4: CDI | H4: FNE | I4: région | J4: Bilan de compétences
A5: COMMERCES DE QUINCAILLERIE | C5: Ingénieur, cadre | D5: AGROALIMENTAIRE | G5: Contrat apprentissage | H5: Fonds alternance | I5: Salarié | J5: Contrat apprentissage
A6: ENSEIGNEMENT PRIVÉ INDÉPENDANT | C6: Ouvrier non qualifié | D6: ART | G6: Contrat de professionnalisation | H6: Fonds conventionnels | J6: Contrat de professionnalisation
A7: ENSEIGNEMENT PRIVÉ NON LUCRATIF | C7: Ouvrier qualifié et HQ | D7: ARTISANAT ART | G7: Contrat pro expérimental | H7: Fonds PDC | J7: Contrat pro expérimental
A8: ENTRETIEN ET LOCATION TEXTILE | C8: Technicien | D8: AUDIOVISUEL MULTIMEDIA | G8: Pro-A | H8: Versement volontaire | J8: Dispositif Insertion par le sport
A9: EXPLOITATIONS FORESTIÈRES ET SCIERIES AGRICOLES | C9: Autre | D9: AUTOMATISME INFORMATIQUE INDUSTRIELLE | G9: CIPI | J9: Hope
A10: HÔTELS, CAFÉS, RESTAURANTS | D10: BANQUE ASSURANCE | G10: CDII | J10: Mission Jeunes
A11: INTERPROFESSION | D11: BATIMENT GROS OEUVRE | G11: CDPI | J11: POEC
A12: MANUTENTION ET NETTOYAGE AÉROPORTUAIRE | D12: BATIMENT SECOND OEUVRE | G12: Autre | J12: POEI (Voir tiers de confiance AKTO)
A13: ORGANISME DE FORMATION | D13: BTP CONCEPTION ORGANISATION | J13: Pro-A
A14: PERSONNEL DE L'ÉGLISE | D14: CHIMIE | J14: Prodiat
A15: PORTAGE SALARIAL | D15: COMMERCE | J15: VAE
A16: PRÉVENTION, SÉCURITÉ | D16: COMMERCE INTERNATIONAL | J16: VAE inversée
A17: PROPRETÉ ET SERVICES | D17: COMMUNICATION ET INFORMATION
A18: RESTAURATION COLLECTIVE | D18: CUIR PEAU
A19: RESTAURATION FERROVIAIRE | D19: DEVELOPPEMENT PROFESSIONNEL ET PERSONNEL
A20: RESTAURATION RAPIDE | D20: DROIT
A21: SERVICE DE L'EAU ET ASSAINISSEMENT | D21: DROIT FISCAL
A22: TRANSPORT ET TRAVAIL AÉRIEN | D22: ECONOMIE
A23: TRAVAIL MÉCANIQUE DU BOIS | D23: ELECTRICITE
A24: TRAVAIL TEMPORAIRE | D24: ELECTRONIQUE
D25: ENCADREMENT MANAGEMENT
D26: ENERGIE
D27: ENVIRONNEMENT AMENAGEMENT
D28: GENIE CLIMATIQUE
D29: GENIE INDUSTRIEL
D30: GESTION COMMERCIALE ACHATS
D31: GESTION FINANCIERE COMPTABILITE
D32: GESTION ORGANISATIONS
D33: GESTION QUALITE
D34: HABILLEMENT
D35: HOTELLERIE RESTAURATION
D36: IMMOBILIER
... D66: TRAVAUX PUBLICS
