Workbook

Sheet Bon à savoir
A5: Lien vers le blog
A7: Notre nouvel outil va vous permettre de créer votre grille des salaires, assurer le suivi des salaires des collaborateurs et définir une rémunération adaptée lors d'un recrutement.
A9: Démarrer la grille des salaires
A11: Définition :
A12: La grille des salaires correspond à l’échelle des salaires dans une organisation. Ce document interne indique notamment quelle est la rémunération (minimum / maximum / median) pour chaque fonction, selon des critères que l’organisation souhaite prendre en compte (ancienneté, niveau de responsabilité, de formation, d’expérience, etc.).
A14: Les objectifs :
A15: Avoir une politique salariale cohérente, transparente et compréhensible. Cela permet à l'entreprise d'éviter l'arbitraire, limiter les conflits, les frustrations et les sentiments d'injustice.
A17: Comment la grille des salaires permet d'atteindre les objectifs ?
A18: Transparence : chacun sait comment fonctionne la rémunération de l’entreprise et peut se renseigner librement à ce sujet
A19: Equité et justice : les rémunérations sont définies par les mêmes critères pour tout le monde et aucune n’est fixée arbitrairement ;
A20: Gestion masse salariale: lorsque l’employeur recrute un nouveau profil, il sait dans quelle case du modèle de rémunération s'intégrera ce salarié. Il peut donc anticiper et contrôler les coûts
A21: Attractivité et marque employeur : Votre entreprise peut paraître très attractive financièrement pour les potentiels talents désireux de la rejoindre à condition de bien communiquer
... A26: Pour en savoir plus, consultez notre article https://laboiteaoutilsdesrh.fr/?p=16308

Sheet Checklist
A4: Lien vers le blog
A6: 5 ETAPES POUR CONSTRUIRE UNE GRILLE AUTOMATISEE
A8: Vous trouverez, ci-dessous les 5 étapes à suivre pour comprendre l'outil et les liens directs à chaque étape.
A10: Etape 1- Visualiser les tables personnalisées et les modifier pour plus de personnalisation
A11: Etape 2- Préparation de votre grille des salaires :
A12: Extraire les données de votre logiciel de paie en suivant les colonnes indiquées (A à J) dans Etablir la grille interne.
A13: Compléter les éléments manquants à l'aide d'un groupe de travail pour les colonnes O à R. (RH, Managers, Direction ...) Votre GPEC et l'évaluation lors des entretiens sont des supports pour plus de subjectivité.
A14: Le but est de définir des rémunérations de référence (calcul automatique) selon la formule suivante :
A15: Salaire de référence x Indice Expérience + Bonus Management + Bonus Ancienneté x Indice de Zone = Rémunération Brute
A16: Décorréler les données permettront de créer une grille de salaires par poste / par équipe pour réaliser un suivi plus fin des salaires et assurer la cohérence.
A17: Etape 3- Visualiser vos grilles par poste ou par secteur en fonction des rémunérations de référence et les rémunérations brutes.
A18: Etape 4- Vérifier la cohérence des salaires en fonction du benchmark
... A23: Il est recommandé de porter connaissance la grille aux salariés après validation de la direction.

Sheet Tables personnalisées 
A4: Lien vers le blog
A5: Tables des éléments personnalisables
A7: Ancienneté & Maitrise / Compétences sur le poste
A8: Paliers | B8: Nom du palier | C8: Définition du palier | D8: Bonus
A9: Palier A | B9: Etude / Prise de poste | C9: intégration humaine et organisationnelle | D9: 0
A10: Palier B | B10: Conquête / Vers l'autonomie | C10: compréhension du business de la société et apport de réponses ajustées aux nécéssités court terme et compréhension de ses propres limites. | D10: 2000
A11: Palier C | B11: Prospérité / Autonome | C11: maîtrise des enjeux du business et transposition pratique dans son pérmiètre d'activité en soutenant notamment activement les collègues. | D11: 4000
A12: Palier D | B12: Étoile du nord / Expert | C12: Influenceur stratégique principalement dans son pôle par sa maîtrise du secteur et ses qualités humaines. | D12: 6000
A13: Palier E | B13: Soleil / Maestro | C13: influenceur à un niveau transversal, débloque les situations et questions les plus complexes. Impose son point de vue par la confiance (humaine et technique) qu'il inspire. | D13: 8000
A14: Palier F | B14: Eureka / Magicien | C14: passage de l'innovation à l'invention et capacité à gérer ce changement en douceur. | D14: 10000
A17: Experience
A18: Paliers | B18: Nom du palier | C18: Définition | D18: Indice
A19: Palier A | B19: Apprentissage | C19: Phase d'apprentissage, de transposition pratique des compétences théoriques. | D19: 1
A20: Palier B | B20: Acquisition des compétences | C20: Phase d'acquisition approfondie des compétences métier et de prise d'autonomie. | D20: 1
A21: Palier C | B21: Prise de recul | C21: Phase de prise de recul sur des compétences maitrisées : recherche d'alternatives et solutions innovantes dans son périmètre métier. | D21: 1.1
A22: Palier D | B22: Integration connaissances transversales | C22: Phase d'intégration de connaissances transversales, de transposition des projets société dans sa stratégie et ses objectifs. | D22: 1.2
A23: Palier E | B23: Innovation | C23: Phase d'innovation sur un pérmimètre fonction large avec maîtrise des enjeux et impacts (matériels et humains) lors de l'implémentation. | D23: 1.3
A24: Palier F | B24: Innovation externe | C24: Phase d'innovation sur un périmètre dont les enjeux dépassent la seule entreprise : impacte sa branche métier dans son ensemble. | D24: 1.4
A28: Management
A29: Paliers | B29: Définition | D29: Montant Bonus
A30: Palier A | B30: Sans management | D30: 0
A31: Palier B | B31: Chef d'équipe | D31: 2000
A32: Palier C | B32: Manager - 5 | D32: 4000
A33: Palier D | B33: Manager + 5 | D33: 6000
A34: Palier D | B34: Responsable / head | D34: 9000
A35: Palier E | B35: VP / Directeur | D35: 12000
A39: Zones Géographiques
A40: Zones | B40: Nom de la zone | C40: Définition | D40: Indice
A41: Zone 1 | B41: Paris | D41: 1.2
A42: Zone 2 | B42: Province | D42: 1
A43: Zone 3 | B43: Télétravail 100% | D43: 0.92
A44: Zone 4 | B44: Hybride | D44: 0.96
A45: Zone 5 | B45: Lyon / Marseille | D45: 1.1
A48: Retour aux étapes

Sheet Etablir la grille interne
H2: Données d'analyse pour créer une grille de salaires
A4: Lien vers le blog
G5: Retour aux étapes | K5: Retour aux étapes | P5: Retour aux étapes | V5: Retour aux étapes
A7: Nom | B7: Prénom | C7: Secteur / Equipe | D7: Poste | E7: CSP | F7: Classification | G7: Date d'entrée au poste | H7: Rémunération Fixe | I7: Rémunération Variable | J7: Primes brutes | K7: Rémunération Brute | L7: Indemnités Net | M7: Participation / Intéressement | N7: Charges Sociales | O7: Experience | P7: Ancienneté & Compétences | Q7: Management | R7: Lieu de travail | S7: Salaire de référence | T7: Indice Expérience | U7: Bonus Ancienneté | V7: Bonus Management | W7: Indice Zone
A8: Dupont | B8: Thierry | C8: Ressources Humaines | D8: Chargé RH | E8: Employé | F8: 100 | G8: 44075 | H8: 22000 | I8: 0 | J8: 0 | K8: =SUM(H8:J8) -> 22000 | L8: 960 | M8: 1500 | N8: =K8*1.5 -> 33000 | O8: Acquisition des compétences | P8: Conquête / Vers l'autonomie | Q8: Sans management | R8: Province | S8: =(K8/W8-U8-V8)/T8 -> 20000 | T8: =VLOOKUP(O8,'Tables personnalisées '!$B$19:$D$24,3,FALSE) -> 1 | U8: =VLOOKUP(P8,'Tables personnalisées '!$B$9:$D$14,3,FALSE) -> 2000 | V8: =VLOOKUP(Q8,'Tables personnalisées '!$B$30:$D$35,3,FALSE) -> 0 | W8: =VLOOKUP(R8,'Tables personnalisées '!$B$41:$D$45,3,FALSE) -> 1
A9: Doly | B9: Albane | C9: Ressources Humaines | D9: RRH | E9: Cadre | F9: 300 | G9: 31356 | H9: 55000 | I9: 3000 | J9: 2000 | K9: =SUM(H9:J9) -> 60000 | L9: 960 | M9: 2000 | N9: =K9*1.5 -> 90000 | O9: Prise de recul | P9: Prospérité / Autonome | Q9: Manager + 5 | R9: Paris | S9: =(K9/(W9)-U9-V9)/(T9) -> 36363.636 | T9: =VLOOKUP(O9,'Tables personnalisées '!$B$19:$D$24,3,FALSE) -> 1.1 | U9: =VLOOKUP(P9,'Tables personnalisées '!$B$9:$D$14,3,FALSE) -> 4000 | V9: =VLOOKUP(Q9,'Tables personnalisées '!$B$30:$D$35,3,FALSE) -> 6000 | W9: =VLOOKUP(R9,'Tables personnalisées '!$B$41:$D$45,3,FALSE) -> 1.2
A10: Hyu | B10: Tessa | C10: Ressources Humaines | D10: Chargé RH | E10: Employé | F10: 100 | G10: 42098 | H10: 33000 | I10: 2000 | J10: 1500 | K10: =SUM(H10:J10) -> 36500 | L10: 960 | M10: 1500 | N10: =K10*1.5 -> 54750 | O10: Integration connaissances transversales | P10: Étoile du nord / Expert | Q10: Sans management | R10: Télétravail 100% | S10: =(K10/W10-U10-V10)/T10 -> 28061.594 | T10: =VLOOKUP(O10,'Tables personnalisées '!$B$19:$D$24,3,FALSE) -> 1.2 | U10: =VLOOKUP(P10,'Tables personnalisées '!$B$9:$D$14,3,FALSE) -> 6000 | V10: =VLOOKUP(Q10,'Tables personnalisées '!$B$30:$D$35,3,FALSE) -> 0 | W10: =VLOOKUP(R10,'Tables personnalisées '!$B$41:$D$45,3,FALSE) -> 0.92
A11: Troppo | B11: Freddy | C11: Marketing | D11: Responsable Marketing | E11: Cadre | F11: 200 | G11: 39054 | H11: 55000 | I11: 3000 | J11: 2000 | K11: =SUM(H11:J11) -> 60000 | L11: 1200 | M11: 2000 | N11: =K11*1.5 -> 90000 | O11: Prise de recul | P11: Prospérité / Autonome | Q11: Manager + 5 | R11: Paris | S11: =(K11/W11-U11-V11)/T11 -> 36363.636 | T11: =VLOOKUP(O11,'Tables personnalisées '!$B$19:$D$24,3,FALSE) -> 1.1 | U11: =VLOOKUP(P11,'Tables personnalisées '!$B$9:$D$14,3,FALSE) -> 4000 | V11: =VLOOKUP(Q11,'Tables personnalisées '!$B$30:$D$35,3,FALSE) -> 6000 | W11: =VLOOKUP(R11,'Tables personnalisées '!$B$41:$D$45,3,FALSE) -> 1.2
A12: Argon | B12: Lola | C12: Marketing | D12: Chargé Marketing | E12: Employé | F12: 100 | G12: 43316 | H12: 25000 | I12: 3000 | J12: 1500 | K12: =SUM(H12:J12) -> 29500 | L12: 960 | M12: 1000 | N12: =K12*1.5 -> 44250 | O12: Prise de recul | P12: Prospérité / Autonome | Q12: Sans management | R12: Hybride | S12: =(K12/W12-U12-V12)/T12 -> 24299.242 | T12: =VLOOKUP(O12,'Tables personnalisées '!$B$19:$D$24,3,FALSE) -> 1.1 | U12: =VLOOKUP(P12,'Tables personnalisées '!$B$9:$D$14,3,FALSE) -> 4000 | V12: =VLOOKUP(Q12,'Tables personnalisées '!$B$30:$D$35,3,FALSE) -> 0 | W12: =VLOOKUP(R12,'Tables personnalisées '!$B$41:$D$45,3,FALSE) -> 0.96
S13: Données calculées | T13: Données calculées | U13: Données calculées | V13: Données calculées | W13: Données calculées

Sheet Grille des salaires
D2: Grille des rémunérations et des salaires de référence
A3: Lien vers le blog | E3: Retour aux étapes
A5: TABLEAUX DE REFERENCE REMUNERATION BRUTE
A7: Secteur / Equipe | B7: COUNTA de Nom | C7: MIN de Rémunération Brute | D7: MEDIAN de Rémunération Brute | E7: MAX de Rémunération Brute
B8: 0 | C8: 0 | D8: #NUM! | E8: 0
A9: Marketing | B9: 2 | C9: 29500 | D9: 44750 | E9: 60000
A10: Ressources Humaines | B10: 3 | C10: 22000 | D10: 36500 | E10: 60000
A14: Poste | B14: COUNTA de Nom | C14: MIN de Rémunération Brute | D14: MEDIAN de Rémunération Brute | E14: MAX de Rémunération Brute
B15: 0 | C15: 0 | D15: #NUM! | E15: 0
A16: Chargé Marketing | B16: 1 | C16: 29500 | D16: 29500 | E16: 29500
A17: Chargé RH | B17: 2 | C17: 22000 | D17: 29250 | E17: 36500
A18: Responsable Marketing | B18: 1 | C18: 60000 | D18: 60000 | E18: 60000
A19: RRH | B19: 1 | C19: 60000 | D19: 60000 | E19: 60000
A23: TABLEAUX DES REMUNERATIONS DE REFERENCE (recalculé via les indices & bonus)
A25: Poste | B25: MIN de Salaire de référence | C25: MEDIAN de Salaire de référence | D25: MAX de Salaire de référence
B26: 0 | C26: #NUM! | D26: 0
A27: Chargé Marketing | B27: 24299.242 | C27: 24299.242 | D27: 24299.242
A28: Chargé RH | B28: 20000 | C28: 24030.797 | D28: 28061.594
A29: Responsable Marketing | B29: 36363.636 | C29: 36363.636 | D29: 36363.636
A30: RRH | B30: 36363.636 | C30: 36363.636 | D30: 36363.636
A33: Secteur / Equipe | B33: MIN de Salaire de référence | C33: MEDIAN de Salaire de référence | D33: MAX de Salaire de référence
B34: 0 | C34: #NUM! | D34: 0
A35: Marketing | B35: 24299.242 | C35: 30331.439 | D35: 36363.636
A36: Ressources Humaines | B36: 20000 | C36: 28061.594 | D36: 36363.636
E39: Retour aux étapes

Sheet Bench externe des salaires
G2: Benchmark des salaires constatés
A3: Lien vers le blog | E3: Retour aux étapes
A6: Postes dans l'entreprise | B6: Min Conventionnel | C6: Min Salaire de Ref Interne | D6: Min Rem Brute Interne | E6: POLE EMPLOI APEC | F6: INDEED | G6: Site métier / branche d'activités | H6: Moyenne | I6: Date Révision | J6: Commentaires
A7: Chargé RH | B7: 18000 | C7: =VLOOKUP(A7,'Grille des salaires'!$A$25:$B$30,2,FALSE) -> 20000 | D7: =VLOOKUP(A7,'Grille des salaires'!$A$14:$E$20,3,FALSE) -> 22000 | E7: 24000 | F7: 28000 | G7: 22000 | H7: =AVERAGE(B7:G7) -> 22333.333 | I7: 44747 | J7: Choisissez des offres types et dans votre zone géographique
A8: RRH | B8: 33000 | C8: =VLOOKUP(A8,'Grille des salaires'!$A$25:$B$30,2,FALSE) -> 36363.636 | D8: =VLOOKUP(A8,'Grille des salaires'!$A$14:$E$20,3,FALSE) -> 60000 | E8: 35000 | F8: 36000 | G8: 30000 | H8: =AVERAGE(B8:G8) -> 38393.939 | I8: 44748
A9: Chargé Marketing | B9: 22000 | C9: =VLOOKUP(A9,'Grille des salaires'!$A$25:$B$30,2,FALSE) -> 24299.242 | D9: =VLOOKUP(A9,'Grille des salaires'!$A$14:$E$20,3,FALSE) -> 29500 | E9: 38000 | F9: 35000 | G9: 35000 | H9: =AVERAGE(B9:G9) -> 30633.207 | I9: 44748
A10: Responsable Marketing | B10: 35000 | C10: =VLOOKUP(A10,'Grille des salaires'!$A$25:$B$30,2,FALSE) -> 36363.636 | D10: =VLOOKUP(A10,'Grille des salaires'!$A$14:$E$20,3,FALSE) -> 60000 | E10: 42000 | F10: 50000 | G10: 38000 | H10: =AVERAGE(B10:G10) -> 43560.606 | I10: 44749
A11: ... | B11: Colonne A saisir | E11: Colonne A saisir | F11: Colonne A saisir | G11: Colonne A saisir | I11: Colonne A saisir | J11: Colonne A saisir si besoin

Sheet Suivi de la grille
G2: Revue des salaires liée au minimum constaté.
A4: Lien vers le blog | F4: Retour aux étapes
A7: Nom | B7: Prénom | C7: Secteur | D7: Poste | E7: Rémunération Brute | F7: Moyenne Marché | G7: Min Secteur | H7: Salaire reference | I7: Min Ref Poste | J7: Min Ref Secteur | K7: Commentaire Marché | L7: Commentaire sur le poste
A8: Dupont | B8: Thierry | C8: Ressources Humaines | D8: Chargé RH | E8: =VLOOKUP(A8,'Etablir la grille interne'!$A$8:$K$12,11,FALSE) -> 22000 | F8: =VLOOKUP(D8,'Bench externe des salaires'!$A$7:$R$14,8,FALSE) -> 22333.333 | G8: =VLOOKUP(C8,'Grille des salaires'!$A$7:$E$11,3,FALSE) -> 22000 | H8: =VLOOKUP(A8,'Etablir la grille interne'!$A$8:$W$12,19,FALSE) -> 20000 | I8: =VLOOKUP(D8,'Grille des salaires'!$A$25:$D$30,2,FALSE) -> 20000 | J8: =VLOOKUP(C8,'Grille des salaires'!$A$33:$D$36,2,FALSE) -> 20000 | K8: =IF(E8<F8,"Alerte ! le marché est plus favorable","ok") -> Alerte ! le marché est plus favorable | L8: =IF(H8=I8,"Restez vigilant à l'évolution sur le poste","ok") -> Restez vigilant à l'évolution sur le poste
A9: Doly | B9: Albane | C9: Ressources Humaines | D9: RRH | E9: =VLOOKUP(A9,'Etablir la grille interne'!$A$8:$K$12,11,FALSE) -> 60000 | F9: =VLOOKUP(D9,'Bench externe des salaires'!$A$7:$R$14,8,FALSE) -> 38393.939 | G9: =VLOOKUP(C9,'Grille des salaires'!$A$7:$E$11,3,FALSE) -> 22000 | H9: =VLOOKUP(A9,'Etablir la grille interne'!$A$8:$W$12,19,FALSE) -> 36363.636 | I9: =VLOOKUP(D9,'Grille des salaires'!$A$25:$D$30,2,FALSE) -> 36363.636 | J9: =VLOOKUP(C9,'Grille des salaires'!$A$33:$D$36,2,FALSE) -> 20000 | K9: =IF(E9<F9,"Alerte ! le marché est plus favorable","ok") -> ok | L9: =IF(H9=I9,"Restez vigilant à l'évolution sur le poste","ok") -> Restez vigilant à l'évolution sur le poste
A10: Hyu | B10: Tessa | C10: Ressources Humaines | D10: Chargé RH | E10: =VLOOKUP(A10,'Etablir la grille interne'!$A$8:$K$12,11,FALSE) -> 36500 | F10: =VLOOKUP(D10,'Bench externe des salaires'!$A$7:$R$14,8,FALSE) -> 22333.333 | G10: =VLOOKUP(C10,'Grille des salaires'!$A$7:$E$11,3,FALSE) -> 22000 | H10: =VLOOKUP(A10,'Etablir la grille interne'!$A$8:$W$12,19,FALSE) -> 28061.594 | I10: =VLOOKUP(D10,'Grille des salaires'!$A$25:$D$30,2,FALSE) -> 20000 | J10: =VLOOKUP(C10,'Grille des salaires'!$A$33:$D$36,2,FALSE) -> 20000 | K10: =IF(E10<F10,"Alerte ! le marché est plus favorable","ok") -> ok | L10: =IF(H10=I10,"Restez vigilant à l'évolution sur le poste","ok") -> ok
A11: Troppo | B11: Freddy | C11: Marketing | D11: Responsable Marketing | E11: =VLOOKUP(A11,'Etablir la grille interne'!$A$8:$K$12,11,FALSE) -> 60000 | F11: =VLOOKUP(D11,'Bench externe des salaires'!$A$7:$R$14,8,FALSE) -> 43560.606 | G11: =VLOOKUP(C11,'Grille des salaires'!$A$7:$E$11,3,FALSE) -> 29500 | H11: =VLOOKUP(A11,'Etablir la grille interne'!$A$8:$W$12,19,FALSE) -> 36363.636 | I11: =VLOOKUP(D11,'Grille des salaires'!$A$25:$D$30,2,FALSE) -> 36363.636 | J11: =VLOOKUP(C11,'Grille des salaires'!$A$33:$D$36,2,FALSE) -> 24299.242 | K11: =IF(E11<F11,"Alerte ! le marché est plus favorable","ok") -> ok | L11: =IF(H11=I11,"Restez vigilant à l'évolution sur le poste","ok") -> Restez vigilant à l'évolution sur le poste
A12: Argon | B12: Lola | C12: Marketing | D12: Chargé Marketing | E12: =VLOOKUP(A12,'Etablir la grille interne'!$A$8:$K$12,11,FALSE) -> 29500 | F12: =VLOOKUP(D12,'Bench externe des salaires'!$A$7:$R$14,8,FALSE) -> 30633.207 | G12: =VLOOKUP(C12,'Grille des salaires'!$A$7:$E$11,3,FALSE) -> 29500 | H12: =VLOOKUP(A12,'Etablir la grille interne'!$A$8:$W$12,19,FALSE) -> 24299.242 | I12: =VLOOKUP(D12,'Grille des salaires'!$A$25:$D$30,2,FALSE) -> 24299.242 | J12: =VLOOKUP(C12,'Grille des salaires'!$A$33:$D$36,2,FALSE) -> 24299.242 | K12: =IF(E12<F12,"Alerte ! le marché est plus favorable","ok") -> Alerte ! le marché est plus favorable | L12: =IF(H12=I12,"Restez vigilant à l'évolution sur le poste","ok") -> Restez vigilant à l'évolution sur le poste

Sheet Calculateur interne de rémunéra
A4: Lien vers le blog | E4: Retour aux étapes
B6: Simulation d'une rémunération sur la base de la grille salariale de l'entreprise
A10: Sur quel poste recrutez-vous ? | C10: Min Sal de références
A11: Responsable Marketing | C11: =VLOOKUP(A11,'Grille des salaires'!A25:D30,2,FALSE) -> 36363.636
A13: Dans quel service ? | C13: Min secteur de références
A14: Marketing | C14: =VLOOKUP(A14,'Grille des salaires'!A33:D36,2,FALSE) -> 24299.242
A16: Quel niveau d'expérience attendez-vous ? | C16: Indice
A17: Prise de recul | C17: =VLOOKUP(A17,'Tables personnalisées '!B19:D24,3,FALSE) -> 1.1
A19: Ce poste contient un rôle de manager ? | C19: Bonus
A20: Manager - 5 | C20: =VLOOKUP(A20,'Tables personnalisées '!B30:D35,3,FALSE) -> 4000
A22: Ou le collaborateur sera situé ? | C22: Indice
A23: Province | C23: =VLOOKUP(A23,'Tables personnalisées '!B41:D45,3,FALSE) -> 1
D25: Minimum Conventionnel | E25: Adequation marché
C26: =(C11*C17+C20)*C23 -> 44000 | D26: =VLOOKUP(A11,'Bench externe des salaires'!A7:H10,2,FALSE) -> 35000 | E26: =VLOOKUP(A11,'Bench externe des salaires'!A7:H10,8,FALSE) -> 43560.606
A28: Fourchette de négociation avec le candidat ? | B28: =C26-(C26*A29) -> 41800 | C28: =C26*A29+C26 -> 46200
A29: 0.05
A32: Calcul de l'impact de l'évolution des compétences et poste | D32: Avantages sociaux dans l'entreprise Montant estimé
A33: Etude / Prise de poste | B33: =C26 -> 44000 | D33: Mutuelle
A34: Conquête / Vers l'autonomie | B34: =VLOOKUP(A34,'Tables personnalisées '!$B$9:$D$14,3,FALSE)+B33 -> 46000 | D34: Tickets Resto
A35: Prospérité / Autonome | B35: =VLOOKUP(A35,'Tables personnalisées '!$B$9:$D$14,3,FALSE)+B34 -> 50000 | D35: ...
A36: Étoile du nord / Expert | B36: =VLOOKUP(A36,'Tables personnalisées '!$B$9:$D$14,3,FALSE)+B35 -> 56000 | D36: ...
A37: Soleil / Maestro | B37: =VLOOKUP(A37,'Tables personnalisées '!$B$9:$D$14,3,FALSE)+B36 -> 64000
A38: Eureka / Magicien | B38: =VLOOKUP(A38,'Tables personnalisées '!$B$9:$D$14,3,FALSE)+B37 -> 74000
